llmcall/__init__.py
llmcall/core.py
llmcall/extract.py
llmcall/extract_utils.py
llmcall/generate.py
llmcall-0.1.0rc1.dist-info/METADATA
llmcall-0.1.0rc1.dist-info/WHEEL
llmcall-0.1.0rc1.dist-info/RECORD
