Metadata-Version: 2.1
Name: llmcall
Version: 0.1.0rc1
Summary: A lite abstraction layer for LLM calls
Home-page: https://github.com/rihoneailabs/llmcall
License: Apache-2.0
Keywords: llm,ai,litellm,structure-outputs,openai,pydantic
Author: Ndamulelo Nemakhavhani
Author-email: info@rihonegroup.com
Requires-Python: >=3.11,<4.0
Classifier: Development Status :: 3 - Alpha
Classifier: Intended Audience :: Developers
Classifier: License :: OSI Approved :: Apache Software License
Classifier: Programming Language :: Python :: 3
Classifier: Programming Language :: Python :: 3.11
Classifier: Programming Language :: Python :: 3.12
Classifier: Programming Language :: Python :: 3.13
Requires-Dist: environs (>=11.2.1,<12.0.0)
Requires-Dist: litellm (>=1.56.4,<2.0.0)
Requires-Dist: openai (>=1.58.1,<2.0.0)
Requires-Dist: pydantic (>=2.0.0)
Requires-Dist: pydantic-settings (>=2.0.0)
Requires-Dist: tenacity (>=9.0.0,<10.0.0)
Project-URL: Repository, https://github.com/rihoneailabs/llmcall.git
